LICENSE
README.md
setup.py
dataskema/__init__.py
dataskema/data_schema.py
dataskema/data_types.py
dataskema/lang.py
dataskema/util.py
dataskema/validator.py
dataskema.egg-info/PKG-INFO
dataskema.egg-info/SOURCES.txt
dataskema.egg-info/dependency_links.txt
dataskema.egg-info/not-zip-safe
dataskema.egg-info/requires.txt
dataskema.egg-info/top_level.txt
dataskema/decorators/__init__.py
dataskema/decorators/args.py
dataskema/decorators/flask.py