Metadata-Version: 2.1
Name: dataskema
Version: 1.6.6
Summary: Data schema to validate parameters easily, quickly and with minimal code
Home-page: https://github.com/lagor-github/dataskema
Author: Luis A. González Rivas
Author-email: lagor55@gmail.com
License: MIT
Platform: UNKNOWN
Classifier: Programming Language :: Python :: 3
Classifier: License :: OSI Approved :: MIT License
Classifier: Development Status :: 5 - Production/Stable
Classifier: Intended Audience :: Developers
Classifier: Operating System :: OS Independent
